FfmpegJiaochengFix1/README.md
FfmpegJiaochengFix1/__init__.py
FfmpegJiaochengFix1/__main__.py
FfmpegJiaochengFix1/file.epub
FfmpegJiaochengFix1/index.html
FfmpegJiaochengFix1/css/__init__.py
FfmpegJiaochengFix1/css/annotations.css
FfmpegJiaochengFix1/css/main.css
FfmpegJiaochengFix1/css/normalize.css
FfmpegJiaochengFix1/css/popup.css
FfmpegJiaochengFix1/font/__init__.py
FfmpegJiaochengFix1/font/fontello.eot
FfmpegJiaochengFix1/font/fontello.svg
FfmpegJiaochengFix1/font/fontello.ttf
FfmpegJiaochengFix1/font/fontello.woff
FfmpegJiaochengFix1/img/__init__.py
FfmpegJiaochengFix1/img/annotator-glyph-sprite.png
FfmpegJiaochengFix1/img/annotator-icon-sprite.png
FfmpegJiaochengFix1/img/apple-touch-icon.png
FfmpegJiaochengFix1/img/cancelfullscreen.png
FfmpegJiaochengFix1/img/close.png
FfmpegJiaochengFix1/img/fullscreen.png
FfmpegJiaochengFix1/img/loader.gif
FfmpegJiaochengFix1/img/menu-icon.png
FfmpegJiaochengFix1/img/save.png
FfmpegJiaochengFix1/img/saved.png
FfmpegJiaochengFix1/img/settings-s.png
FfmpegJiaochengFix1/img/settings.png
FfmpegJiaochengFix1/img/star.png
FfmpegJiaochengFix1/js/__init__.py
FfmpegJiaochengFix1/js/epub.js
FfmpegJiaochengFix1/js/epub.min.js
FfmpegJiaochengFix1/js/epub.min.map
FfmpegJiaochengFix1/js/hooks.min.js
FfmpegJiaochengFix1/js/hooks.min.map
FfmpegJiaochengFix1/js/reader.js
FfmpegJiaochengFix1/js/reader.js.map
FfmpegJiaochengFix1/js/reader.min.js
FfmpegJiaochengFix1/js/reader.min.map
FfmpegJiaochengFix1/js/hooks/__init__.py
FfmpegJiaochengFix1/js/hooks/extensions/__init__.py
FfmpegJiaochengFix1/js/hooks/extensions/highlight.js
FfmpegJiaochengFix1/js/libs/__init__.py
FfmpegJiaochengFix1/js/libs/jquery.min.js
FfmpegJiaochengFix1/js/libs/localforage.min.js
FfmpegJiaochengFix1/js/libs/screenfull.js
FfmpegJiaochengFix1/js/libs/screenfull.min.js
FfmpegJiaochengFix1/js/libs/zip.min.js
FfmpegJiaochengFix1/js/plugins/__init__.py
FfmpegJiaochengFix1/js/plugins/hypothesis.js
FfmpegJiaochengFix1/js/plugins/search.js
ffmpeg_jiaocheng_fix1-2025.3.25.1.dist-info/METADATA
ffmpeg_jiaocheng_fix1-2025.3.25.1.dist-info/WHEEL
ffmpeg_jiaocheng_fix1-2025.3.25.1.dist-info/entry_points.txt
ffmpeg_jiaocheng_fix1-2025.3.25.1.dist-info/top_level.txt
ffmpeg_jiaocheng_fix1-2025.3.25.1.dist-info/RECORD
